vsw/__init__.py
vsw/__main__.py
vsw/cli.py
vsw/log.py
vsw/utils.py
vsw/views.py
vsw/__pycache__/__init__.cpython-38.pyc
vsw/commands/__init__.py
vsw/commands/agent.py
vsw/commands/attest.py
vsw/commands/exit.py
vsw/commands/help.py
vsw/commands/init.py
vsw/commands/list.py
vsw/commands/provision.py
vsw/commands/publish.py
vsw/commands/register.py
vsw/commands/revoke.py
vsw/commands/setup.py
vsw/commands/verify.py
vsw/conf/__init__.py
vsw/conf/aries_logging_config.ini
vsw/conf/dns.txt
vsw/conf/genesis.txt
vsw/conf/local_tunnel.sh
vsw/conf/logging_config.ini
vsw/conf/vsw.ini
vsw/controller/__init__.py
vsw/controller/server.py
vsw/controller/__pycache__/__init__.cpython-38.pyc
vsw/controller/__pycache__/server.cpython-38.pyc
vsw/dao/__init__.py
vsw/dao/vsw_dao.py
vsw/grpc/__init__.py
vsw/grpc/client.py
vsw/grpc/server.py
vsw/grpc/vsw_pb2.py
vsw/grpc/vsw_pb2_grpc.py
vsw-0.0.28.dist-info/LICENSE
vsw-0.0.28.dist-info/METADATA
vsw-0.0.28.dist-info/WHEEL
vsw-0.0.28.dist-info/entry_points.txt
vsw-0.0.28.dist-info/top_level.txt
vsw-0.0.28.dist-info/RECORD
