Metadata-Version: 2.1
Name: vsw
Version: 0.0.28
Summary: Command line tool for interacting with the verifiable software repository
Home-page: https://github.com/verifiablesoftware/vsw.git
Author: Futurewei Technologies, Inc.
Author-email: chu.wenjing@gmail.com
License: UNKNOWN
Platform: UNKNOWN
Requires-Python: >=3.6
License-File: LICENSE
Requires-Dist: pkginfo (>=1.4.2)
Requires-Dist: readme-renderer (>=21.0)
Requires-Dist: requests-toolbelt (!=0.9.0,>=0.8.0)
Requires-Dist: setuptools (>=45)
Requires-Dist: setuptools-scm (>=1.15)
Requires-Dist: rich
Requires-Dist: terminaltables
Requires-Dist: version-parser
Requires-Dist: py-multibase
Requires-Dist: tqdm (>=4.14)
Requires-Dist: pretend (>=1.0.9)
Requires-Dist: aries-cloudagent-vsw (==0.0.3)
Requires-Dist: python3-indy (>=1.11.1<2)
Requires-Dist: aiohttp (~=3.6.2)
Requires-Dist: aiohttp-apispec (==2.2.1)
Requires-Dist: aiohttp-cors (~=0.7.0)
Requires-Dist: apispec (~=3.3.0)
Requires-Dist: async-timeout (~=3.0.1)
Requires-Dist: base58 (~=2.0.0)
Requires-Dist: Markdown (~=3.1.1)
Requires-Dist: marshmallow (==3.5.1)
Requires-Dist: msgpack (~=0.6.1)
Requires-Dist: prompt-toolkit (~=2.0.9)
Requires-Dist: pynacl (~=1.3.0)
Requires-Dist: requests (~=2.23.0)
Requires-Dist: validators (~=0.18.2)
Requires-Dist: pyld (==2.0.1)
Requires-Dist: py-multicodec (==0.2.1)
Requires-Dist: keyring (>=15.1)
Requires-Dist: rfc3986 (>=1.4.0)
Requires-Dist: colorama (>=0.4.3)
Requires-Dist: flask (==1.1.4)
Requires-Dist: Jinja2 (<3.0)
Requires-Dist: wheel (>=0.36.2)
Requires-Dist: importlib-metadata ; python_version < "3.8"
